semantic_bibtool/__init__.py
semantic_bibtool/__main__.py
semantic_bibtool-0.2.1.dist-info/LICENSE
semantic_bibtool-0.2.1.dist-info/METADATA
semantic_bibtool-0.2.1.dist-info/WHEEL
semantic_bibtool-0.2.1.dist-info/entry_points.txt
semantic_bibtool-0.2.1.dist-info/top_level.txt
semantic_bibtool-0.2.1.dist-info/RECORD
