Metadata-Version: 2.1
Name: semantic-bibtool
Version: 0.2.1
Summary: Command Line Tool for generating bibliography files using Semantic Scholar API
Author-email: Robert Dyro <robert.dyro@gmail.com>
Project-URL: Homepage, https://github.com/rdyro/semantic_bibtool
Project-URL: Bug Tracker, https://github.com/rdyro/semantic_bibtool
Classifier: Programming Language :: Python :: 3
Classifier: License :: OSI Approved :: MIT License
Classifier: Operating System :: OS Independent
Requires-Python: >=3.7
License-File: LICENSE
Requires-Dist: numpy
Requires-Dist: pandas
Requires-Dist: tqdm
Requires-Dist: requests
